Datorama/__init__.py
Datorama/classes/__init__.py
Datorama/classes/connection.py
Datorama/classes/datastream.py
Datorama/classes/datorama.py
Datorama/classes/errors.py
Datorama/classes/run_stat.py
Datorama/classes/timer.py
Datorama/classes/workspace.py
pyDatorama-0.11.dist-info/LICENSE
pyDatorama-0.11.dist-info/METADATA
pyDatorama-0.11.dist-info/WHEEL
pyDatorama-0.11.dist-info/top_level.txt
pyDatorama-0.11.dist-info/RECORD
