Metadata-Version: 2.1
Name: pyDatorama
Version: 0.11
Summary: A Python API wrapping library for Salesforce's datorama platform.
Home-page: UNKNOWN
Author: meow1928
Author-email: UNKNOWN
License: UNKNOWN
Platform: UNKNOWN
Requires-Dist: pandas
